pyrusgeom/__init__.py
pyrusgeom/angle_deg.py
pyrusgeom/circle_2d.py
pyrusgeom/convex_hull.py
pyrusgeom/geom_2d.py
pyrusgeom/line_2d.py
pyrusgeom/math_values.py
pyrusgeom/matrix_2d.py
pyrusgeom/polygon_2d.py
pyrusgeom/ray_2d.py
pyrusgeom/rect_2d.py
pyrusgeom/region_2d.py
pyrusgeom/sector_2d.py
pyrusgeom/segment_2d.py
pyrusgeom/size_2d.py
pyrusgeom/soccer_math.py
pyrusgeom/triangle_2d.py
pyrusgeom/vector_2d.py
pyrusgeom-0.1.2.dist-info/METADATA
pyrusgeom-0.1.2.dist-info/WHEEL
pyrusgeom-0.1.2.dist-info/licenses/LICENSE
pyrusgeom-0.1.2.dist-info/RECORD
