Metadata-Version: 2.1
Name: pyrusgeom
Version: 0.1.2
Summary: A package for handling geometry and math in SS2D
Project-URL: Homepage, https://github.com/Cyrus2D/PyrusGeom
Project-URL: Bug Tracker, https://github.com/Cyrus2D/PyrusGeom/issues
Author-email: Cyrus 2D Team <info@cyrus2d.com>
License-File: LICENSE
Classifier: Development Status :: 3 - Alpha
Classifier: License :: OSI Approved :: GNU General Public License v3 (GPLv3)
Classifier: Operating System :: OS Independent
Classifier: Programming Language :: Python :: 3
Requires-Python: >=3.7
